.gitignore
.svnignore
CONTRIBUTORS.rst
MANIFEST.in
README.rst
setup.cfg
setup.py
docs/CHANGES.rst
docs/INSTALL.txt
docs/LICENSE.EUPL
docs/LICENSE.GPL
docs/LICENSE.txt
src/slc/__init__.py
src/slc.seminarportal.egg-info/PKG-INFO
src/slc.seminarportal.egg-info/SOURCES.txt
src/slc.seminarportal.egg-info/dependency_links.txt
src/slc.seminarportal.egg-info/entry_points.txt
src/slc.seminarportal.egg-info/namespace_packages.txt
src/slc.seminarportal.egg-info/not-zip-safe
src/slc.seminarportal.egg-info/requires.txt
src/slc.seminarportal.egg-info/top_level.txt
src/slc/seminarportal/__init__.py
src/slc/seminarportal/config.py
src/slc/seminarportal/configure.zcml
src/slc/seminarportal/interfaces.py
src/slc/seminarportal/permissions.py
src/slc/seminarportal/relations.xml
src/slc/seminarportal/setuphandlers.py
src/slc/seminarportal/skins.zcml
src/slc/seminarportal/utils.py
src/slc/seminarportal/vocabulary.py
src/slc/seminarportal/Extensions/__init__.py
src/slc/seminarportal/Extensions/create_seminar_test_data.py
src/slc/seminarportal/browser/__init__.py
src/slc/seminarportal/browser/configure.zcml
src/slc/seminarportal/browser/interfaces.py
src/slc/seminarportal/browser/views.py
src/slc/seminarportal/browser/resources/jquery.bigtarget.1.0.1.js
src/slc/seminarportal/browser/resources/portlets_speaker.js
src/slc/seminarportal/browser/resources/seminar_view.js
src/slc/seminarportal/browser/templates/seminar_macros.pt
src/slc/seminarportal/browser/templates/seminar_roster.pt
src/slc/seminarportal/browser/templates/seminar_search.pt
src/slc/seminarportal/browser/templates/seminar_view.pt
src/slc/seminarportal/browser/templates/seminarfolder_view.pt
src/slc/seminarportal/browser/templates/speaker_view.pt
src/slc/seminarportal/browser/templates/speakersfolder_view.pt
src/slc/seminarportal/browser/templates/speech_add_helper_page.pt
src/slc/seminarportal/browser/templates/speech_summary.pt
src/slc/seminarportal/browser/templates/speech_view.pt
src/slc/seminarportal/browser/templates/speechvenue_view.pt
src/slc/seminarportal/browser/templates/speechvenuesfolder_view.pt
src/slc/seminarportal/content/__init__.py
src/slc/seminarportal/content/configure.zcml
src/slc/seminarportal/content/seminar.py
src/slc/seminarportal/content/speaker.py
src/slc/seminarportal/content/speakersfolder.py
src/slc/seminarportal/content/speech.py
