Metadata-Version: 1.1
Name: slc.seminarportal
Version: 1.4.7
Summary: A Seminar and Conference websites built on Plone
Home-page: http://pypi.python.org/pypi/slc.seminarportal/
Author: Syslab.com GmbH
Author-email: info@syslab.com
License: GPL + EUPL
Keywords: seminar section subsite
Platform: UNKNOWN
Classifier: Framework :: Plone
Classifier: Framework :: Zope2
Classifier: Framework :: Zope3
Classifier: Programming Language :: Python
Classifier: Topic :: Software Development :: Libraries :: Python Modules
Classifier: License :: OSI Approved :: GNU General Public License (GPL)
Classifier: License :: OSI Approved :: European Union Public Licence 1.1 (EUPL 1.1)
